{
  "uuid": "be70d495-389e-4026-bfe2-dfa3943c24d6",
  "name": "Coordinate ring",
  "link": "https://en.wikipedia.org/wiki/Affine_variety",
  "summary": "In algebraic geometry, an affine variety or affine algebraic variety is a certain kind of algebraic variety that can be described as a subset of an affine space.\nMore formally, an affine algebraic set is the set of the common zeros over an algebraically closed field k of some family of polynomials in the polynomial ring \n  \n    \n      \n        k\n        [\n        \n          x\n          \n            1\n          \n        \n        ,\n        …\n        ,\n        \n          x\n          \n            n\n",
  "subject": null,
  "head": null,
  "count": 0,
  "previous_conjectures": [],
  "references": []
}