{
  "uuid": "5c126d4b-7b13-44e4-9ff4-8c5ba947dd05",
  "name": "Core model",
  "link": "https://en.wikipedia.org/wiki/Core_model",
  "summary": "In set theory, the core model is a definable inner model of the universe of all sets. Even though set theorists refer to \"the core model\", it is not a uniquely identified mathematical object. Rather, it is a class of inner models that under the right set-theoretic assumptions have very special properties, most notably covering properties. Intuitively, the core model is \"the largest canonical inner model there is\", (here \"canonical\" is an undefined term)p. 28 and is typically associated with a la",
  "subject": null,
  "head": null,
  "count": 0,
  "previous_conjectures": [],
  "references": []
}